smart_contracts_for_testing/abi/BaseBoringBatchable.json
smart_contracts_for_testing/abi/BentoBoxV1.json
smart_contracts_for_testing/abi/BoringBatchable.json
smart_contracts_for_testing/abi/BoringERC20.json
smart_contracts_for_testing/abi/BoringFactory.json
smart_contracts_for_testing/abi/BoringMath.json
smart_contracts_for_testing/abi/BoringMath128.json
smart_contracts_for_testing/abi/BoringMath32.json
smart_contracts_for_testing/abi/BoringMath64.json
smart_contracts_for_testing/abi/BoringOwnable.json
smart_contracts_for_testing/abi/BoringOwnableData.json
smart_contracts_for_testing/abi/CloneRewarderTime.json
smart_contracts_for_testing/abi/CloneRewarderTimeDual.json
smart_contracts_for_testing/abi/ComplexRewarder.json
smart_contracts_for_testing/abi/ComplexRewarderTime.json
smart_contracts_for_testing/abi/Domain.json
smart_contracts_for_testing/abi/ERC20.json
smart_contracts_for_testing/abi/ERC20Data.json
smart_contracts_for_testing/abi/ERC20Mock.json
smart_contracts_for_testing/abi/IBatchFlashBorrower.json
smart_contracts_for_testing/abi/IBentoBoxV1.json
smart_contracts_for_testing/abi/IBentoBoxWithdraw.json
smart_contracts_for_testing/abi/IERC20.json
smart_contracts_for_testing/abi/IERC20Uniswap.json
smart_contracts_for_testing/abi/IFlashBorrower.json
smart_contracts_for_testing/abi/IKashiWithdrawFee.json
smart_contracts_for_testing/abi/IMasterChef.json
smart_contracts_for_testing/abi/IMasterChefV2.json
smart_contracts_for_testing/abi/IMasterContract.json
smart_contracts_for_testing/abi/IMigrator.json
smart_contracts_for_testing/abi/IMigratorChef.json
smart_contracts_for_testing/abi/IMiniChefV2.json
smart_contracts_for_testing/abi/IOracle.json
smart_contracts_for_testing/abi/IRewarder.json
smart_contracts_for_testing/abi/IStrategy.json
smart_contracts_for_testing/abi/ISwapper.json
smart_contracts_for_testing/abi/IUniswapV2Callee.json
smart_contracts_for_testing/abi/IUniswapV2ERC20.json
smart_contracts_for_testing/abi/IUniswapV2Factory.json
smart_contracts_for_testing-0.1.0.dist-info/WHEEL
smart_contracts_for_testing-0.1.0.dist-info/METADATA
smart_contracts_for_testing-0.1.0.dist-info/RECORD
