Metadata-Version: 2.1
Name: smart-contracts-for-testing
Version: 0.1.0
Summary: Popular Solidity smart contracts to be used in testing: ERC-20, Uniswap v2, etc.
Home-page: https://tradingstrategy.ai
License: MIT
Keywords: ethereum,cryptocurrency,uniswap,erc-20,pancakeswap,sushiswap,polygon,web3
Author: Mikko Ohtamaa
Author-email: mikko@capitalgram.com
Requires-Python: >=3.8,<4.0
Classifier: License :: OSI Approved :: MIT License
Classifier: Programming Language :: Python :: 3
Classifier: Programming Language :: Python :: 3.10
Classifier: Programming Language :: Python :: 3.8
Classifier: Programming Language :: Python :: 3.9
Provides-Extra: docs
Requires-Dist: Brownie (>=0.5.1,<0.6.0)
Requires-Dist: Sphinx (>=4.4.0,<5.0.0); extra == "docs"
Requires-Dist: sphinx-rtd-theme (>=1.0.0,<2.0.0); extra == "docs"
Requires-Dist: sphinx-sitemap (>=2.2.0,<3.0.0); extra == "docs"
Requires-Dist: web3[tester] (>=5.26.0,<6.0.0)
Project-URL: Repository, https://github.com/tradingstrategy-ai/smart-contracts-for-testing
